kickbox/__init__.py
kickbox/client.py
kickbox/api/__init__.py
kickbox/api/kickbox.py
kickbox/error/__init__.py
kickbox/error/client_error.py
kickbox/http_client/__init__.py
kickbox/http_client/auth_handler.py
kickbox/http_client/error_handler.py
kickbox/http_client/request_handler.py
kickbox/http_client/response.py
kickbox/http_client/response_handler.py
kickbox-2.0.4.dist-info/METADATA
kickbox-2.0.4.dist-info/WHEEL
kickbox-2.0.4.dist-info/top_level.txt
kickbox-2.0.4.dist-info/RECORD
